{
	"easycom": {
		"autoscan": true,
		"custom": {
			"custom-tabbar": "@/components/custom-tabbar.vue",
			"head-return": "@/components/head-return.vue",
			"app-toast": "@/components/app-toast.vue"
		}
	},
	"pages": [{
		"path": "pages/splash/index",
		"style": {
			"navigationStyle": "custom",
			"navigationBarTitleText": "",
			"app-plus": {
				"titleNView": false
			}
		}
	}, {
		"path": "pages/tabbar-container/index",
		"style": {
			"navigationStyle": "custom",
			"navigationBarTitleText": "",
			"app-plus": {
				"titleNView": false
			}
		}
	}, {
		"path": "pages/device/index",
		"style": {
			"navigationStyle": "custom",
			"navigationBarTitleText": "",
			"app-plus": {
				"titleNView": false
			}
		}
	}, {
		"path": "pages/chat/index",
		"style": {
			"navigationStyle": "custom",
			"navigationBarTitleText": "",
			"app-plus": {
				"titleNView": false
			}
		}
	}, {
		"path": "pages/personal/index",
		"style": {
			"navigationStyle": "custom",
			"navigationBarTitleText": "",
			"app-plus": {
				"titleNView": false
			}
		}
	}, {
		"path": "pages/provisioning/index",
		"style": {
			"navigationStyle": "custom",
			"navigationBarTitleText": "",
			"app-plus": {
				"titleNView": false
			}
		}
	},
	{
		"path" : "pages/device/role",
		"style" : 
		{
			"navigationStyle": "custom",
			"navigationBarTitleText": "",
			"app-plus": {
				"titleNView": false
			}
		}
	},
	{
		"path" : "pages/device/behavior",
		"style" : 
		{
			"navigationStyle": "custom",
			"navigationBarTitleText": "",
			"app-plus": {
				"titleNView": false
			}
		}
	},	{
		"path" : "pages/personal/my-devices",
		"style" : 
		{
			"navigationStyle": "custom",
			"navigationBarTitleText": "",
			"app-plus": {
				"titleNView": false
			}
		}
	},
	{
		"path" : "pages/personal/exchange",
		"style" : 
		{
			"navigationStyle": "custom",
			"navigationBarTitleText": "",
			"app-plus": {
				"titleNView": false
			}
		}
	},
	{
		"path" : "pages/device/setting",
		"style" : 
		{
			"navigationStyle": "custom",
			"navigationBarTitleText": "",
			"app-plus": {
				"titleNView": false
			}
		}
	},
	{
		"path" : "pages/personal/setting",
		"style" : 
		{
			"navigationStyle": "custom",
			"navigationBarTitleText": "",
			"app-plus": {
				"titleNView": false
			}
		}
	},	
	{
		"path" : "pages/personal/user-info",
		"style" : 
		{
			"navigationStyle": "custom",
			"navigationBarTitleText": "",
			"app-plus": {
				"titleNView": false
			}
		}
	},
	{
		"path" : "pages/login/index",
		"style" : 
		{
			"navigationStyle": "custom",
			"navigationBarTitleText": "",
			"app-plus": {
				"titleNView": false
			}
		}
	},

	{
		"path" : "pages/test/toast-test",
		"style" : 
		{
			"navigationStyle": "custom",
			"navigationBarTitleText": "",
			"app-plus": {
				"titleNView": false
			}
		}
	},
	{
		"path" : "pages/device/recommend",
		"style" : 
		{
			"navigationStyle": "custom",
			"navigationBarTitleText": "",
			"app-plus": {
				"titleNView": false
			}
		}
	}],
	"globalStyle": {
		"navigationBarTextStyle": "black",
		"navigationBarTitleText": "uni-app",
		"navigationBarBackgroundColor": "#fff",
		"backgroundColor": "#fff",
		"app-plus": {
			"titleNView": false,
			"statusBarStyle": "dark"
		}
	},

	"uniIdRouter": {}
}